brfunds/__init__.py
brfunds/api.py
brfunds/brfunds.py
brfunds-0.2.1.dist-info/LICENSE
brfunds-0.2.1.dist-info/METADATA
brfunds-0.2.1.dist-info/WHEEL
brfunds-0.2.1.dist-info/top_level.txt
brfunds-0.2.1.dist-info/RECORD
