Metadata-Version: 2.1
Name: brfunds
Version: 0.2.1
Summary: Package to scrap data from brazilian funds
Home-page: https://github.com/Phactos/brfunds
Author: Phactos
Project-URL: Bug Tracker, https://github.com/Phactos/brfunds/issues
Classifier: Programming Language :: Python :: 3
Classifier: Programming Language :: Python :: 3.6
Classifier: Programming Language :: Python :: 3.7
Classifier: Programming Language :: Python :: 3.8
Classifier: Programming Language :: Python :: 3.9
Classifier: Programming Language :: Python :: 3.10
Classifier: Programming Language :: Python :: 3.11
Classifier: License :: OSI Approved :: MIT License
Classifier: Operating System :: OS Independent
Requires-Python: >=3.6
License-File: LICENSE
Requires-Dist: requests
Requires-Dist: numpy
Requires-Dist: pandas
